setup.py
network_tester/__init__.py
network_tester/commands.py
network_tester/counters.py
network_tester/errors.py
network_tester/experiment.py
network_tester/results.py
network_tester/version.py
network_tester.egg-info/PKG-INFO
network_tester.egg-info/SOURCES.txt
network_tester.egg-info/dependency_links.txt
network_tester.egg-info/requires.txt
network_tester.egg-info/top_level.txt
network_tester/binaries/network_tester.aplx
network_tester/binaries/reinjector.aplx