Metadata-Version: 1.0
Name: network-tester
Version: 0.1.10
Summary: SpiNNaker network experiment library.
Home-page: https://github.com/project-rig/network_tester
Author: Jonathan Heathcote
Author-email: UNKNOWN
License: GPLv2
Platform: UNKNOWN
